README.md
setup.py
SKPD/BlockLasso.py
SKPD/SKPD.py
SKPD/__init__.py
SKPD/criterion.py
SKPD/interface.py
SKPD/my_operator.py
SKPD/visualization.py
SKPD.egg-info/PKG-INFO
SKPD.egg-info/SOURCES.txt
SKPD.egg-info/dependency_links.txt
SKPD.egg-info/requires.txt
SKPD.egg-info/top_level.txt