Metadata-Version: 2.1
Name: SKPD
Version: 0.0.6
Summary: image regression
Home-page: https://github.com/SanyouWu/SKPD
Author: Sanyou WU
Author-email: sanyouwsy@gmail.com
License: MIT Licence
Platform: all
Requires-Python: >=3.7.0
